pytrovich/__init__.py
pytrovich/detector.py
pytrovich/enums.py
pytrovich/gender_models.py
pytrovich/maker.py
pytrovich/meta.py
pytrovich/normalizer.py
pytrovich/rule_models.py
pytrovich/rules_data.py
pytrovich/petrovich-rules/.git
pytrovich/petrovich-rules/.travis.yml
pytrovich/petrovich-rules/LICENSE
pytrovich/petrovich-rules/README.md
pytrovich/petrovich-rules/Rakefile
pytrovich/petrovich-rules/gender.json
pytrovich/petrovich-rules/gender.yml
pytrovich/petrovich-rules/rules.json
pytrovich/petrovich-rules/rules.yml
pytrovich-0.0.3.dist-info/LICENSE
pytrovich-0.0.3.dist-info/METADATA
pytrovich-0.0.3.dist-info/WHEEL
pytrovich-0.0.3.dist-info/top_level.txt
pytrovich-0.0.3.dist-info/RECORD
