Metadata-Version: 2.1
Name: pytrovich
Version: 0.0.3
Summary: pytrovich: a Python port of an inflector for Russian anthroponyms developed by petrovich team: https://github.com/petrovich
Home-page: https://github.com/petrovich/pytrovich
Author: Anton Alekseev
Author-email: anton.m.alexeye@gmail.com
License: UNKNOWN
Keywords: nlp,morphology,russian language
Platform: UNKNOWN
Classifier: Programming Language :: Python :: 3
Classifier: License :: OSI Approved :: MIT License
Classifier: Operating System :: OS Independent
Requires-Python: >=3.6
License-File: LICENSE
